xrobot_launcher.py
xeus_robot-0.4.4.data/data/nlohmann_json.natvis
xeus_robot-0.4.4.data/data/share/jupyter/kernels/xrobot/kernel.js
xeus_robot-0.4.4.data/data/share/jupyter/kernels/xrobot/kernel.json
xeus_robot-0.4.4.data/data/share/jupyter/kernels/xrobot/logo-32x32.png
xeus_robot-0.4.4.data/data/share/jupyter/kernels/xrobot/logo-64x64.png
xrobot/__init__.py
xrobot/xrobot_extension.cp37-win_amd64.pyd
xeus_robot-0.4.4.dist-info/LICENSE
xeus_robot-0.4.4.dist-info/METADATA
xeus_robot-0.4.4.dist-info/WHEEL
xeus_robot-0.4.4.dist-info/top_level.txt
xeus_robot-0.4.4.dist-info/RECORD
