Metadata-Version: 2.1
Name: xeus-robot
Version: 0.4.4
Summary: A wheel for xeus-robot
Home-page: UNKNOWN
Author: Sylvain Corlay, Johan Mabille, Martin Renou
License: UNKNOWN
Platform: UNKNOWN
License-File: LICENSE
Requires-Dist: Pillow (==8.3.1)
Requires-Dist: robotframework-interpreter (<0.8,>=0.7.5)
Requires-Dist: robotframework-lsp
Requires-Dist: jupyterlab-robotmode
Requires-Dist: xeus-python (==0.13.5)
